gaktest/__init__.py
gaktest/py.typed
pytest_gak/__init__.py
pytest_gak/py.typed
pytest_gak-2.0.1.dist-info/METADATA
pytest_gak-2.0.1.dist-info/WHEEL
pytest_gak-2.0.1.dist-info/entry_points.txt
pytest_gak-2.0.1.dist-info/top_level.txt
pytest_gak-2.0.1.dist-info/RECORD
