Metadata-Version: 2.4
Name: pytest-gak
Version: 2.0.1
Summary: A Pytest plugin and command line tool for interactive testing with Pytest
Author-email: Josh Holbrook <josh.holbrook@gmail.com>
License: Apache-2.0
Classifier: Framework :: Pytest
Requires-Python: >=3.11
Requires-Dist: click
Requires-Dist: rich
